{
    "format": 2,
    "name": "n30k4_42",
    "n": 30,
    "k": 4,
    "optimal_solution": 12689.791015625,
    "x_values": [
        -5015.67,
        -10357.5,
        -5081.43,
        -5798.57,
        -6298.38,
        -6039.92,
        -6094.74,
        -6083.39,
        -9332.64,
        -5899.83,
        -5385.66,
        -5125.02,
        -6121.88,
        -8163.21,
        -5599.17,
        -5817.28,
        -7743.78,
        -6933.79,
        -4854.37,
        -6264.52,
        -7228.0,
        -6065.41,
        -5246.24,
        -5352.19,
        -5800.64,
        -7513.6,
        -6035.26,
        -7319.8,
        -5839.24,
        -5603.66
    ],
    "y_values": [
        2909.02,
        4229.9,
        2836.61,
        2484.72,
        2104.0,
        2726.98,
        2771.47,
        2120.83,
        4194.8,
        2777.19,
        2364.84,
        2814.65,
        2562.3,
        2359.46,
        2349.29,
        2747.17,
        2311.13,
        3065.66,
        3016.81,
        2936.6,
        2643.22,
        2952.19,
        2787.01,
        2594.79,
        3000.1,
        2454.83,
        2873.92,
        2465.81,
        3211.91,
        2216.82
    ]
}