{
    "format": 2,
    "name": "n90k8_62",
    "n": 90,
    "k": 8,
    "optimal_solution": 38758.2578125,
    "x_values": [
        -4303.32,
        -10357.5,
        -5704.14,
        -5709.93,
        -5664.12,
        -4821.5,
        -4752.28,
        -6298.38,
        -5796.36,
        -8448.44,
        -5245.63,
        -6906.17,
        -5058.67,
        -7775.6,
        -5894.53,
        -6056.24,
        -7242.67,
        -5599.17,
        -5734.86,
        -9613.13,
        -5817.28,
        -6146.39,
        -7253.95,
        -6467.97,
        -8504.68,
        -6687.73,
        -5782.44,
        -6522.52,
        -8275.68,
        -5688.3,
        -6035.26,
        -7500.33,
        -6081.78,
        -5513.3,
        -7741.15,
        -10769.1,
        -6589.17,
        -5953.15,
        -5642.06,
        -6534.95,
        -5650.84,
        -6002.71,
        -5842.42,
        -7955.43,
        -4917.1,
        -5811.31,
        -6376.8,
        -6520.37,
        -7650.33,
        -6221.99,
        -4469.28,
        -5108.32,
        -7293.6,
        -5125.02,
        -5113.52,
        -5271.0,
        -8448.31,
        -5622.97,
        -8163.21,
        -5124.98,
        -6190.2,
        -7769.44,
        -7228.0,
        -4932.84,
        -8278.54,
        -5362.92,
        -5800.64,
        -3644.93,
        -6744.5,
        -8095.0,
        -8422.34,
        -4567.65,
        -8270.56,
        -7319.8,
        -5702.52,
        -5108.93,
        -6060.69,
        -5081.43,
        -8380.59,
        -5261.48,
        -6498.27,
        -6171.89,
        -6610.92,
        -5485.93,
        -7664.49,
        -5198.28,
        -8528.19,
        -5577.48,
        -6725.58,
        -7907.33
    ],
    "y_values": [
        5701.62,
        4229.9,
        2459.86,
        2658.69,
        2312.69,
        3061.67,
        3095.56,
        2104.0,
        3012.19,
        2616.77,
        2908.83,
        3448.55,
        3073.09,
        3178.67,
        2421.5,
        2891.65,
        2683.25,
        2349.29,
        2761.14,
        4425.1,
        2747.17,
        2752.79,
        2745.8,
        2874.42,
        3043.82,
        3239.01,
        2971.98,
        2445.01,
        2539.11,
        2048.78,
        2873.92,
        2699.15,
        3076.08,
        2492.45,
        3219.36,
        1363.24,
        2056.5,
        2747.82,
        2095.81,
        2701.62,
        1696.66,
        2792.62,
        2952.63,
        2499.54,
        2950.86,
        2815.13,
        2400.82,
        2248.7,
        3456.09,
        2428.67,
        3186.15,
        3156.64,
        3477.58,
        2814.65,
        2813.17,
        2545.94,
        2612.12,
        1971.86,
        2359.46,
        2827.16,
        2811.75,
        2962.23,
        2643.22,
        3371.41,
        2731.33,
        2981.8,
        3000.1,
        3290.24,
        2683.69,
        2260.48,
        2579.99,
        1276.08,
        2378.33,
        2465.81,
        1888.81,
        2958.27,
        3022.99,
        2836.61,
        2622.72,
        2974.43,
        2309.52,
        3342.29,
        2698.07,
        3014.47,
        2226.38,
        2978.08,
        3361.29,
        2768.24,
        2604.37,
        4315.91
    ]
}