{
    "format": 5,
    "name": "n70k7_38",
    "n": 70,
    "k": 7,
    "optimal_solution": 32749.419921875,
    "x_values": [
        -5096.27,
        -9287.82,
        -4303.32,
        -5959.5,
        -5661.16,
        -6193.98,
        -5785.13,
        -5554.22,
        -6363.98,
        -4149.04,
        -6753.6,
        -4917.1,
        -7793.97,
        -11011.9,
        -5341.75,
        -8463.32,
        -5773.31,
        -7496.88,
        -5485.93,
        -6632.67,
        -5972.88,
        -6906.17,
        -5551.32,
        -8176.92,
        -5517.35,
        -5962.96,
        -7775.6,
        -5108.32,
        -6097.23,
        -5585.92,
        -5271.0,
        -5666.77,
        -6498.95,
        -6737.94,
        -5622.97,
        -5124.98,
        -4942.97,
        -6729.65,
        -9613.13,
        -5817.28,
        -7743.78,
        -7769.44,
        -8476.31,
        -6364.15,
        -6322.14,
        -9013.16,
        -5127.67,
        -7228.0,
        -5246.24,
        -7714.57,
        -6389.26,
        -6156.0,
        -4597.05,
        -4552.73,
        -6550.1,
        -6232.28,
        -7500.33,
        -7690.35,
        -7731.13,
        -5693.08,
        -8104.15,
        -8095.0,
        -8270.56,
        -5022.26,
        -6060.69,
        -10907.3,
        -6589.17,
        -6324.33,
        -5831.77,
        -5118.47
    ],
    "y_values": [
        2947.1,
        4028.41,
        5701.62,
        2880.14,
        2414.86,
        2750.12,
        2920.73,
        3002.82,
        3228.21,
        3189.55,
        2091.31,
        2950.86,
        3429.24,
        1518.8,
        3053.49,
        3369.09,
        2878.79,
        3163.43,
        3014.47,
        2498.08,
        2555.87,
        3448.55,
        2980.19,
        3182.87,
        3001.69,
        2236.4,
        3178.67,
        3156.64,
        2771.87,
        2434.03,
        2545.94,
        2759.7,
        4058.49,
        2450.65,
        1971.86,
        2827.16,
        2985.49,
        1920.88,
        4425.1,
        2747.17,
        2311.13,
        2962.23,
        3145.48,
        3232.53,
        3096.27,
        3750.93,
        2809.7,
        2643.22,
        2787.01,
        2432.03,
        3041.71,
        2920.75,
        3169.38,
        3131.15,
        2024.58,
        2668.97,
        2699.15,
        3282.06,
        2816.4,
        2408.16,
        2356.74,
        2260.48,
        2378.33,
        2885.68,
        3022.99,
        1472.22,
        2056.5,
        2878.6,
        2919.0,
        2814.13
    ]
}