{
    "format": 2,
    "name": "n110k2_31",
    "n": 110,
    "k": 2,
    "optimal_solution": 95184.6953125,
    "x_values": [
        -6890.91,
        -5632.62,
        -10357.5,
        -5142.33,
        -4821.5,
        -5885.55,
        -6502.02,
        -5341.75,
        -8448.44,
        -7496.88,
        -6141.59,
        -6963.69,
        -4909.96,
        -5450.17,
        -5517.35,
        -5058.67,
        -4913.12,
        -6332.2,
        -5640.47,
        -5585.92,
        -5644.81,
        -7242.67,
        -6379.87,
        -5734.86,
        -6729.65,
        -5598.34,
        -7253.95,
        -6467.97,
        -6264.52,
        -5127.67,
        -5533.55,
        -8504.68,
        -4597.05,
        -5919.29,
        -6081.78,
        -6155.92,
        -5312.4,
        -10769.1,
        -10907.3,
        -6589.17,
        -5953.15,
        -5642.06,
        -5273.15,
        -9287.82,
        -5913.71,
        -6538.33,
        -6534.95,
        -6068.06,
        -5272.4,
        -5842.42,
        -7955.43,
        -7793.97,
        -5837.05,
        -5811.31,
        -6679.25,
        -6376.8,
        -8170.06,
        -6177.23,
        -4937.25,
        -4469.28,
        -5962.96,
        -5014.68,
        -5996.43,
        -6315.55,
        -5028.78,
        -6223.79,
        -5113.52,
        -7736.85,
        -6628.87,
        -5252.81,
        -8163.21,
        -6190.2,
        -5527.38,
        -6490.06,
        -8476.31,
        -5271.9,
        -4932.84,
        -6389.26,
        -5362.92,
        -5470.42,
        -3644.93,
        -8501.11,
        -8422.34,
        -5702.52,
        -7372.49,
        -5839.24,
        -5603.66,
        -8452.53,
        -4953.51,
        -5959.5,
        -8113.56,
        -6193.98,
        -5015.67,
        -5790.83,
        -5571.47,
        -6363.98,
        -4149.04,
        -8460.28,
        -6039.92,
        -6171.89,
        -5622.77,
        -5164.44,
        -7664.49,
        -8511.34,
        -8176.92,
        -5322.9,
        -6380.49,
        -5096.73,
        -5572.55,
        -7919.99
    ],
    "y_values": [
        2242.06,
        2838.55,
        4229.9,
        2719.89,
        3061.67,
        2924.21,
        2078.8,
        3053.49,
        2616.77,
        3163.43,
        2100.22,
        3234.25,
        2926.78,
        2963.26,
        3001.69,
        3073.09,
        2927.93,
        2902.59,
        2649.8,
        2434.03,
        2867.43,
        2683.25,
        2691.39,
        2761.14,
        1920.88,
        2018.32,
        2745.8,
        2874.42,
        2936.6,
        2809.7,
        2910.94,
        3043.82,
        3169.38,
        2968.58,
        3076.08,
        2098.24,
        2782.73,
        1363.24,
        1472.22,
        2056.5,
        2747.82,
        2095.81,
        2783.06,
        4028.41,
        2922.17,
        2702.62,
        2701.62,
        2942.42,
        2766.44,
        2952.63,
        2499.54,
        3429.24,
        2624.85,
        2815.13,
        2819.1,
        2400.82,
        2352.86,
        2976.16,
        2970.81,
        3186.15,
        2236.4,
        3058.17,
        2498.9,
        2180.68,
        2878.6,
        2069.72,
        2813.17,
        2848.33,
        2850.79,
        3131.36,
        2359.46,
        2811.75,
        2794.27,
        2065.86,
        3145.48,
        2545.16,
        3371.41,
        3041.71,
        2981.8,
        2984.36,
        3290.24,
        3105.35,
        2579.99,
        1888.81,
        3604.78,
        3211.91,
        2216.82,
        3289.4,
        3139.57,
        2880.14,
        3293.02,
        2750.12,
        2909.02,
        2758.59,
        2789.37,
        3228.21,
        3189.55,
        3264.98,
        2726.98,
        3342.29,
        3355.96,
        2778.82,
        2226.38,
        3399.16,
        3182.87,
        2687.48,
        2936.07,
        2835.26,
        2839.81,
        2261.17
    ]
}