{
    "format": 5,
    "name": "n110k6_74",
    "n": 110,
    "k": 6,
    "optimal_solution": 53517.7734375,
    "x_values": [
        -5096.27,
        -7369.09,
        -4303.32,
        -5785.13,
        -5830.85,
        -5664.12,
        -6298.38,
        -6502.02,
        -5972.88,
        -4907.1,
        -5450.17,
        -7878.31,
        -4913.12,
        -8275.34,
        -5057.96,
        -5640.47,
        -5585.92,
        -5894.53,
        -5644.81,
        -5872.29,
        -5734.86,
        -6729.65,
        -7253.95,
        -6467.97,
        -5738.11,
        -6264.52,
        -6364.15,
        -7357.75,
        -6762.95,
        -10206.6,
        -4916.54,
        -6687.73,
        -7714.57,
        -5782.44,
        -7513.6,
        -6550.1,
        -7500.33,
        -5919.29,
        -4388.17,
        -5312.4,
        -5022.26,
        -7741.15,
        -6589.17,
        -5953.15,
        -5642.06,
        -6534.95,
        -6068.06,
        -5798.57,
        -11011.9,
        -5811.31,
        -5612.35,
        -8170.06,
        -5778.64,
        -5030.68,
        -5541.05,
        -5962.96,
        -5014.68,
        -5899.83,
        -5028.78,
        -6223.79,
        -5490.8,
        -8448.31,
        -7736.85,
        -6737.94,
        -6026.31,
        -6190.2,
        -5414.57,
        -5193.52,
        -6933.79,
        -5060.97,
        -7769.44,
        -6490.06,
        -7228.0,
        -4932.84,
        -5433.61,
        -5246.24,
        -5352.19,
        -6156.0,
        -5470.42,
        -8501.11,
        -7731.13,
        -6805.46,
        -4567.65,
        -8431.72,
        -7372.49,
        -6060.69,
        -6477.72,
        -6660.82,
        -6681.55,
        -5959.5,
        -5661.16,
        -8113.56,
        -6193.98,
        -6446.49,
        -5081.43,
        -5582.85,
        -6363.98,
        -5261.48,
        -6039.92,
        -6498.27,
        -5622.77,
        -5198.28,
        -8176.92,
        -5322.9,
        -5531.36,
        -5096.73,
        -5219.97,
        -5544.54,
        -8326.35,
        -7907.33
    ],
    "y_values": [
        2947.1,
        2424.18,
        5701.62,
        2920.73,
        2331.9,
        2312.69,
        2104.0,
        2078.8,
        2555.87,
        2907.78,
        2963.26,
        3531.75,
        2927.93,
        2706.05,
        2818.45,
        2649.8,
        2434.03,
        2421.5,
        2867.43,
        2242.9,
        2761.14,
        1920.88,
        2745.8,
        2874.42,
        2924.92,
        2936.6,
        3232.53,
        2194.38,
        2514.78,
        4480.01,
        2881.39,
        3239.01,
        2432.03,
        2971.98,
        2454.83,
        2024.58,
        2699.15,
        2968.58,
        3101.07,
        2782.73,
        2885.68,
        3219.36,
        2056.5,
        2747.82,
        2095.81,
        2701.62,
        2942.42,
        2484.72,
        1518.8,
        2815.13,
        2968.25,
        2352.86,
        2269.14,
        2870.1,
        1780.86,
        2236.4,
        3058.17,
        2777.19,
        2878.6,
        2069.72,
        3208.34,
        2612.12,
        2848.33,
        2450.65,
        2101.97,
        2811.75,
        3056.1,
        2760.53,
        3065.66,
        2933.11,
        2962.23,
        2065.86,
        2643.22,
        3371.41,
        2471.69,
        2787.01,
        2594.79,
        2920.75,
        2984.36,
        3105.35,
        2816.4,
        2033.06,
        1276.08,
        2554.75,
        3604.78,
        3022.99,
        2247.34,
        2936.57,
        3009.12,
        2880.14,
        2414.86,
        3293.02,
        2750.12,
        2571.41,
        2836.61,
        3221.59,
        3228.21,
        2974.43,
        2726.98,
        2309.52,
        3355.96,
        2978.08,
        3182.87,
        2687.48,
        1845.89,
        2835.26,
        2746.26,
        2494.33,
        3220.01,
        4315.91
    ]
}