{
    "format": 2,
    "name": "n40k10_50",
    "n": 40,
    "k": 10,
    "optimal_solution": 9030.8115234375,
    "x_values": [
        -5096.27,
        -6068.06,
        -5650.84,
        -5571.47,
        -6002.71,
        -4149.04,
        -5796.36,
        -5341.75,
        -7496.88,
        -6141.59,
        -6632.67,
        -6094.74,
        -5108.32,
        -7293.6,
        -5243.09,
        -5385.66,
        -6719.09,
        -6097.23,
        -5522.89,
        -4961.26,
        -5585.92,
        -6498.95,
        -5599.17,
        -6688.46,
        -5193.52,
        -5817.28,
        -6364.15,
        -5451.57,
        -7714.57,
        -4597.05,
        -8275.68,
        -5688.3,
        -6550.1,
        -5712.79,
        -8501.11,
        -5513.3,
        -5546.08,
        -4388.17,
        -8270.56,
        -5702.52
    ],
    "y_values": [
        2947.1,
        2942.42,
        1696.66,
        2789.37,
        2792.62,
        3189.55,
        3012.19,
        3053.49,
        3163.43,
        2100.22,
        2498.08,
        2771.47,
        3156.64,
        3477.58,
        2849.91,
        2364.84,
        3448.62,
        2771.87,
        2264.71,
        2920.16,
        2434.03,
        4058.49,
        2349.29,
        2265.19,
        2760.53,
        2747.17,
        3232.53,
        2487.02,
        2432.03,
        3169.38,
        2539.11,
        2048.78,
        2024.58,
        1918.83,
        3105.35,
        2492.45,
        3009.12,
        3101.07,
        2378.33,
        1888.81
    ]
}