{
    "format": 5,
    "name": "n30k2_67",
    "n": 30,
    "k": 2,
    "optimal_solution": 21368.919921875,
    "x_values": [
        -5632.62,
        -5959.5,
        -5798.57,
        -5142.33,
        -8460.28,
        -6171.89,
        -8170.06,
        -6177.23,
        -6221.99,
        -5541.05,
        -6999.1,
        -6315.55,
        -5544.54,
        -5640.47,
        -7242.59,
        -6026.31,
        -6146.39,
        -7253.95,
        -4934.35,
        -7357.75,
        -7228.0,
        -4932.84,
        -5246.24,
        -6687.73,
        -6522.52,
        -8394.66,
        -6081.78,
        -7319.8,
        -5831.77,
        -7390.17
    ],
    "y_values": [
        2838.55,
        2880.14,
        2484.72,
        2719.89,
        3264.98,
        3342.29,
        2352.86,
        2976.16,
        2428.67,
        1780.86,
        3332.66,
        2180.68,
        2494.33,
        2649.8,
        2842.6,
        2101.97,
        2752.79,
        2745.8,
        2889.85,
        2194.38,
        2643.22,
        3371.41,
        2787.01,
        3239.01,
        2445.01,
        2665.83,
        3076.08,
        2465.81,
        2919.0,
        3095.29
    ]
}