{
    "format": 5,
    "name": "n50k5_22",
    "n": 50,
    "k": 5,
    "optimal_solution": 21606.962890625,
    "x_values": [
        -6890.91,
        -6538.33,
        -5216.07,
        -7036.07,
        -6534.95,
        -5292.52,
        -5664.12,
        -6875.52,
        -8223.61,
        -8170.06,
        -4927.67,
        -5997.68,
        -8029.09,
        -5198.28,
        -5972.88,
        -8511.34,
        -5551.32,
        -9332.64,
        -5014.68,
        -7878.31,
        -8275.34,
        -5125.02,
        -5057.96,
        -4961.26,
        -5463.16,
        -5572.55,
        -7736.85,
        -5872.29,
        -7743.78,
        -6146.39,
        -4889.42,
        -6322.14,
        -9013.16,
        -7715.07,
        -5533.55,
        -7231.96,
        -4916.54,
        -5782.44,
        -5362.92,
        -5882.04,
        -5470.42,
        -6506.2,
        -6550.1,
        -6232.28,
        -7500.33,
        -5712.79,
        -6081.78,
        -5108.93,
        -6324.33,
        -6477.72
    ],
    "y_values": [
        2242.06,
        2702.62,
        2805.86,
        2433.68,
        2701.62,
        3055.77,
        2312.69,
        1900.55,
        2444.14,
        2352.86,
        2945.78,
        2316.13,
        3013.51,
        2978.08,
        2555.87,
        3399.16,
        2980.19,
        4194.8,
        3058.17,
        3531.75,
        2706.05,
        2814.65,
        2818.45,
        2920.16,
        2979.17,
        2839.81,
        2848.33,
        2242.9,
        2311.13,
        2752.79,
        2976.07,
        3096.27,
        3750.93,
        2779.99,
        2910.94,
        3484.63,
        2881.39,
        2971.98,
        2981.8,
        2841.94,
        2984.36,
        3148.06,
        2024.58,
        2668.97,
        2699.15,
        1918.83,
        3076.08,
        2958.27,
        2878.6,
        2247.34
    ]
}